lightwind/__init__.py
lightwind/chat.py
lightwind/client.py
lightwind/inference.proto
lightwind/inference_pb2.py
lightwind/inference_pb2.pyi
lightwind/inference_pb2_grpc.py
lightwind-0.1.0.dist-info/METADATA
lightwind-0.1.0.dist-info/WHEEL
lightwind-0.1.0.dist-info/RECORD
